[
    {
        "name": "Houssan A. Hijazi",
        "designation": "Development",
        "linkedin": "https://www.linkedin.com/in/hussanhijazi",
        "github": "https://github.com/hussanhijazi",
        "profileImage": "",
        "website": "https://www.hussan.com.br"
    },
    {
        "name": "Valmir Barbosa",
        "designation": "Development",
        "twitter": "https://twitter.com/valmirphp",
        "linkedin": "https://www.linkedin.com/in/valmirbarbosa/",
        "github": "https://github.com/valmirphp",
        "profileImage": "",
        "website": ""
    },
    {
        "name": "Andre Queiroz",
        "designation": "Development",
        "twitter": "https://twitter.com/andrequeirozcom",
        "linkedin": "https://www.linkedin.com/in/andre-queiroz-4936b0b8/",
        "github": "https://github.com/andrequeiroz2/",
        "profileImage": "",
        "website": ""
    },
    {
        "name": "Name",
        "designation": "Development",
        "twitter": "https://twitter.com/",
        "linkedin": "https://linkedin.com/",
        "github": "https://github.com/",
        "profileImage": "",
        "website": "https://github.com"
    },
    {
        "name": "Name",
        "designation": "Development",
        "twitter": "https://twitter.com/",
        "linkedin": "",
        "github": "https://github.com/",
        "profileImage": "",
        "website": ""
    }
]
